ble_hrm_server-0.2.3.dist-info/licenses/LICENSE
hrm/__init__.py
hrm/__main__.py
hrm/bt_client.py
hrm/server.py
hrm/ts_db.py
ble_hrm_server-0.2.3.dist-info/METADATA
ble_hrm_server-0.2.3.dist-info/WHEEL
ble_hrm_server-0.2.3.dist-info/entry_points.txt
ble_hrm_server-0.2.3.dist-info/top_level.txt
ble_hrm_server-0.2.3.dist-info/RECORD
