Metadata-Version: 2.4
Name: ble-hrm-server
Version: 0.2.3
Summary: A Python MCP server for Bluetooth Low Energy (BLE) Heart Rate Monitoring. Connects to BLE HRM devices, monitors heart rate, and provides tools for heart rate data analysis and visualization.
Author: GENE WU.
Maintainer-email: Gene Wu <genewoo@gmail.com>
Keywords: ble,hrm,mcp,llm
Requires-Python: <3.14,>=3.10
License-File: LICENSE
Requires-Dist: bleak>=0.22.3
Requires-Dist: dotenv>=0.9.9
Requires-Dist: fastmcp>=2.3.4
Requires-Dist: matplotlib>=3.10.3
Requires-Dist: pytest>=8.3.5
Requires-Dist: qiniu>=7.16.0
Dynamic: license-file
